README.md
pyproject.toml
pipmake/Builder.py
pipmake/__init__.py
pipmake/api.py
pipmake.egg-info/PKG-INFO
pipmake.egg-info/SOURCES.txt
pipmake.egg-info/dependency_links.txt
pipmake.egg-info/requires.txt
pipmake.egg-info/top_level.txt