Metadata-Version: 2.4
Name: pipmake
Version: 0.0.3
Requires-Python: >=3.8
Requires-Dist: editables
